polarpandas/__init__.py
polarpandas/_exceptions.py
polarpandas/_index_manager.py
polarpandas/_sql_utils.py
polarpandas/datetime.py
polarpandas/frame.py
polarpandas/index.py
polarpandas/io.py
polarpandas/lazyframe.py
polarpandas/operations.py
polarpandas/py.typed
polarpandas/series.py
polarpandas/utils.py
polarpandas-0.9.0.dist-info/licenses/LICENSE
polarpandas-0.9.0.dist-info/METADATA
polarpandas-0.9.0.dist-info/WHEEL
polarpandas-0.9.0.dist-info/entry_points.txt
polarpandas-0.9.0.dist-info/top_level.txt
polarpandas-0.9.0.dist-info/RECORD
