Metadata-Version: 2.4
Name: polarpandas
Version: 0.9.0
Summary: A pandas-compatible API layer built on top of Polars for high-performance data manipulation
Author-email: Odos Matthews <odosmatthews@gmail.com>
Maintainer-email: Odos Matthews <odosmatthews@gmail.com>
License: MIT
Project-URL: Homepage, https://github.com/eddiethedean/polarpandas
Project-URL: Repository, https://github.com/eddiethedean/polarpandas
Project-URL: Documentation, https://github.com/eddiethedean/polarpandas#readme
Project-URL: Bug Tracker, https://github.com/eddiethedean/polarpandas/issues
Keywords: pandas,polars,dataframe,data-analysis,performance
Classifier: Development Status :: 4 - Beta
Classifier: Intended Audience :: Developers
Classifier: Intended Audience :: Science/Research
Classifier: Operating System :: OS Independent
Classifier: Programming Language :: Python :: 3
Classifier: Programming Language :: Python :: 3.8
Classifier: Programming Language :: Python :: 3.9
Classifier: Programming Language :: Python :: 3.10
Classifier: Programming Language :: Python :: 3.11
Classifier: Programming Language :: Python :: 3.12
Classifier: Topic :: Scientific/Engineering
Classifier: Topic :: Software Development :: Libraries :: Python Modules
Classifier: Typing :: Typed
Requires-Python: >=3.8
License-File: LICENSE
Requires-Dist: polars>=0.15.8
Provides-Extra: dev
Requires-Dist: pytest>=7.0.0; extra == "dev"
Requires-Dist: pytest-cov>=4.0.0; extra == "dev"
Requires-Dist: ruff>=0.1.0; extra == "dev"
Requires-Dist: black>=22.0.0; extra == "dev"
Requires-Dist: sqlalchemy>=1.4.0; extra == "dev"
Requires-Dist: types-tabulate>=0.9.0; extra == "dev"
Provides-Extra: test
Requires-Dist: pytest>=7.0.0; extra == "test"
Requires-Dist: pytest-cov>=4.0.0; extra == "test"
Requires-Dist: pytest-benchmark>=4.0.0; extra == "test"
Requires-Dist: pandas>=1.5.0; extra == "test"
Requires-Dist: numpy>=1.20.0; extra == "test"
Requires-Dist: sqlalchemy>=1.4.0; extra == "test"
Requires-Dist: types-tabulate>=0.9.0; extra == "test"
Provides-Extra: pandas
Requires-Dist: pandas>=1.5.0; extra == "pandas"
Provides-Extra: numpy
Requires-Dist: numpy>=1.20.0; extra == "numpy"
Provides-Extra: excel
Requires-Dist: openpyxl>=3.0.0; extra == "excel"
Requires-Dist: xlsxwriter>=3.0.0; extra == "excel"
Provides-Extra: hdf5
Requires-Dist: h5py>=3.0.0; extra == "hdf5"
Requires-Dist: tables>=3.8.0; extra == "hdf5"
Provides-Extra: html
Requires-Dist: lxml>=4.0.0; extra == "html"
Requires-Dist: html5lib>=1.1; extra == "html"
Provides-Extra: spss
Requires-Dist: pyreadstat>=1.0.0; extra == "spss"
Provides-Extra: sas
Requires-Dist: sas7bdat>=2.0.0; extra == "sas"
Provides-Extra: xarray
Requires-Dist: xarray>=2022.0.0; extra == "xarray"
Provides-Extra: clipboard
Requires-Dist: pyperclip>=1.8.0; extra == "clipboard"
Provides-Extra: formatting
Requires-Dist: tabulate>=0.9.0; extra == "formatting"
Requires-Dist: types-tabulate>=0.9.0; extra == "formatting"
Provides-Extra: sqlalchemy
Requires-Dist: sqlalchemy>=1.4.0; extra == "sqlalchemy"
Provides-Extra: docs
Requires-Dist: sphinx>=5.0.0; extra == "docs"
Requires-Dist: sphinx-rtd-theme>=1.0.0; extra == "docs"
Provides-Extra: all
Requires-Dist: pandas>=1.5.0; extra == "all"
Requires-Dist: numpy>=1.20.0; extra == "all"
Requires-Dist: openpyxl>=3.0.0; extra == "all"
Requires-Dist: xlsxwriter>=3.0.0; extra == "all"
Requires-Dist: h5py>=3.0.0; extra == "all"
Requires-Dist: tables>=3.8.0; extra == "all"
Requires-Dist: lxml>=4.0.0; extra == "all"
Requires-Dist: html5lib>=1.1; extra == "all"
Requires-Dist: pyreadstat>=1.0.0; extra == "all"
Requires-Dist: sas7bdat>=2.0.0; extra == "all"
Requires-Dist: xarray>=2022.0.0; extra == "all"
Requires-Dist: pyperclip>=1.8.0; extra == "all"
Requires-Dist: tabulate>=0.9.0; extra == "all"
Requires-Dist: sqlalchemy>=1.4.0; extra == "all"
Requires-Dist: types-tabulate>=0.9.0; extra == "all"
Dynamic: license-file
